pyCloudCompare/__init__.py
pyCloudCompare/pyCloudCompare.py
pyCloudCompareCLI-0.3.2.dist-info/LICENSE
pyCloudCompareCLI-0.3.2.dist-info/METADATA
pyCloudCompareCLI-0.3.2.dist-info/WHEEL
pyCloudCompareCLI-0.3.2.dist-info/top_level.txt
pyCloudCompareCLI-0.3.2.dist-info/RECORD
