Metadata-Version: 2.1
Name: pyCloudCompareCLI
Version: 0.3.2
Summary: Python Wrapper for CloudCompare CLI 
Home-page: https://github.com/dwoiwode/pyCloudCompareCLI
Author: dwoiwode
Author-email: 
License: MIT
Classifier: Programming Language :: Python :: 3
Classifier: License :: OSI Approved :: MIT License
Classifier: Operating System :: OS Independent
Requires-Python: >=3.6
License-File: LICENSE
